MANIFEST.in
README.md
setup.py
auto_cmake/__init__.py
auto_cmake/auto_cmake.py
auto_cmake/auto_cmake_android.py
auto_cmake/auto_cmake_exe.py
auto_cmake/auto_cmake_indexer.py
auto_cmake/auto_cmake_ios.py
auto_cmake/auto_cmake_lib_shared_mac.py
auto_cmake/auto_cmake_lib_shared_nux.py
auto_cmake/auto_cmake_lib_shared_win.py
auto_cmake/auto_cmake_stm32.py
auto_cmake.egg-info/PKG-INFO
auto_cmake.egg-info/SOURCES.txt
auto_cmake.egg-info/dependency_links.txt
auto_cmake.egg-info/requires.txt
auto_cmake.egg-info/top_level.txt
tests/__init__.py
tests/test_auto_cmake.py
tests/test_auto_cmake_exe.py
tests/test_auto_cmake_lib_shared_android.py
tests/test_auto_cmake_lib_shared_mac.py
tests/test_auto_cmake_lib_shared_win.py
tests/test_auto_cmake_lib_static_ios.py